fluentql/__init__.py
fluentql/base_types.py
fluentql/errors.py
fluentql/function.py
fluentql/query.py
fluentql/type_checking.py
fluentql/types.py
fluentql-0.1.1.dist-info/LICENSE
fluentql-0.1.1.dist-info/METADATA
fluentql-0.1.1.dist-info/WHEEL
fluentql-0.1.1.dist-info/top_level.txt
fluentql-0.1.1.dist-info/RECORD
