Metadata-Version: 2.1
Name: fluentql
Version: 0.1.1
Summary: Lightweight and intuitive Python SQL query builder.
Home-page: https://github.com/RaduG/fluentql
Author: Radu Ghitescu
Author-email: radu.ghitescu@gmail.com
License: MIT
Platform: UNKNOWN
Classifier: Development Status :: 3 - Alpha
Classifier: Intended Audience :: Developers
Requires-Python: >=3.6
